irating_ircalculator-0.0.1.dist-info/licenses/LICENSE
ircalculator/__init__.py
ircalculator/calculator.py
irating_ircalculator-0.0.1.dist-info/METADATA
irating_ircalculator-0.0.1.dist-info/WHEEL
irating_ircalculator-0.0.1.dist-info/top_level.txt
irating_ircalculator-0.0.1.dist-info/RECORD
