Metadata-Version: 2.4
Name: irating-ircalculator
Version: 0.0.1
Summary: Simple gain-lost irating calculator.
Author-email: Víctor Arnelas <arrecio@gmail.com>
License-Expression: MIT
Project-URL: Homepage, https://github.com/arrecio/ircalculator/
Project-URL: Issues, https://github.com/arrecio/ircalculator/issues
Classifier: Programming Language :: Python :: 3
Classifier: Operating System :: OS Independent
Requires-Python: >=3.9
License-File: LICENSE
Dynamic: license-file
